CHANGELOG.md
LICENSE
MANIFEST.in
README.md
setup.py
dayonetools/__init__.py
dayonetools/main.py
dayonetools.egg-info/PKG-INFO
dayonetools.egg-info/SOURCES.txt
dayonetools.egg-info/dependency_links.txt
dayonetools.egg-info/entry_points.txt
dayonetools.egg-info/requires.txt
dayonetools.egg-info/top_level.txt
dayonetools/services/__init__.py
dayonetools/services/habit_list.py
dayonetools/services/idonethis.py
dayonetools/services/nikeplus.py
dayonetools/services/pedometerpp.py
dayonetools/services/sleep_cycle.py
dayonetools/services/twitter.py