Metadata-Version: 1.1
Name: dayonetools
Version: 1.3.0
Summary: Tools to import multiple services into Day One Journal
Home-page: https://github.com/durden/dayonetools
Author: Luke Lee
Author-email: durdenmisc@gmail.com
License: MIT
Platform: any
Classifier: Development Status :: 4 - Beta
Classifier: Environment :: Console
Classifier: Intended Audience :: Developers
Classifier: Intended Audience :: End Users/Desktop
Classifier: Natural Language :: English
Classifier: Operating System :: OS Independent
Classifier: Topic :: System :: Archiving
